word_document_reader/__init__.py
word_document_reader/main.py
word_document_reader/tools.py
word_document_reader/utils.py
word_document_reader_mcp-1.0.4.dist-info/METADATA
word_document_reader_mcp-1.0.4.dist-info/WHEEL
word_document_reader_mcp-1.0.4.dist-info/entry_points.txt
word_document_reader_mcp-1.0.4.dist-info/top_level.txt
word_document_reader_mcp-1.0.4.dist-info/RECORD
