Metadata-Version: 2.4
Name: word-document-reader-mcp
Version: 1.0.4
Summary: Word文档内容读取MCP服务 - 提供文档内容读取相关功能
Author-email: Word MCP Services <support@example.com>
License: MIT
Requires-Python: >=3.10
Requires-Dist: python-docx>=1.1.0
Requires-Dist: fastmcp>=2.8.1
